classifier_toolkit/eda/__init__.py
classifier_toolkit/eda/bivariate_analysis.py
classifier_toolkit/eda/eda_toolkit.py
classifier_toolkit/eda/feature_engineering.py
classifier_toolkit/eda/first_glance.py
classifier_toolkit/eda/univariate_analysis.py
classifier_toolkit/eda/visualizations.py
classifier_toolkit/eda/warnings/__init__.py
classifier_toolkit/eda/warnings/automated_warnings.py
classifier_toolkit/eda/warnings/default_warnings.py
classifier_toolkit/feature_selection/__init__.py
classifier_toolkit/feature_selection/base.py
classifier_toolkit/feature_selection/embedded_methods/__init__.py
classifier_toolkit/feature_selection/embedded_methods/elastic_net.py
classifier_toolkit/feature_selection/feature_stability.py
classifier_toolkit/feature_selection/meta_selector.py
classifier_toolkit/feature_selection/utils/__init__.py
classifier_toolkit/feature_selection/utils/data_handling.py
classifier_toolkit/feature_selection/utils/plottings.py
classifier_toolkit/feature_selection/utils/scoring.py
classifier_toolkit/feature_selection/wrapper_methods/__init__.py
classifier_toolkit/feature_selection/wrapper_methods/bayesian_search.py
classifier_toolkit/feature_selection/wrapper_methods/boruta.py
classifier_toolkit/feature_selection/wrapper_methods/rfe.py
classifier_toolkit/feature_selection/wrapper_methods/rfe_catboost.py
classifier_toolkit/feature_selection/wrapper_methods/sequential_selection.py
classifier_toolkit/model_training/__init__.py
classifier_toolkit/model_training/hyper_parameter_tuning/__init__.py
classifier_toolkit/model_training/hyper_parameter_tuning/tuner.py
classifier_toolkit/model_training/models/__init__.py
classifier_toolkit/model_training/models/base.py
classifier_toolkit/model_training/models/ensemble_methods.py
classifier_toolkit/model_training/utils/__init__.py
classifier_toolkit/model_training/utils/params.py
classifier_toolkit-0.2.2.dist-info/LICENSE
classifier_toolkit-0.2.2.dist-info/METADATA
classifier_toolkit-0.2.2.dist-info/WHEEL
classifier_toolkit-0.2.2.dist-info/RECORD
