Metadata-Version: 2.1
Name: classifier-toolkit
Version: 0.2.2
Summary: 
Author: senih.yilmaz
Author-email: senih.yilmaz@qonto.com
Requires-Python: >=3.9,<3.13
Classifier: Programming Language :: Python :: 3
Classifier: Programming Language :: Python :: 3.9
Classifier: Programming Language :: Python :: 3.10
Classifier: Programming Language :: Python :: 3.11
Classifier: Programming Language :: Python :: 3.12
Requires-Dist: catboost (>=1.2.2,<2.0.0)
Requires-Dist: category-encoders (>=2.6.3,<3.0.0)
Requires-Dist: colorama (>=0.4.6,<0.5.0)
Requires-Dist: lightgbm (>=4.5.0,<5.0.0)
Requires-Dist: matplotlib (>=3.9.2,<4.0.0)
Requires-Dist: numpy (<2.0)
Requires-Dist: optuna (>=3.5.0,<4.0.0)
Requires-Dist: pandas (>=2.2.0,<3.0.0)
Requires-Dist: polars (>=1.2.1,<2.0.0)
Requires-Dist: pyarrow (>=18.0.0,<19.0.0)
Requires-Dist: scikit-learn (>=1.4.0,<2.0.0)
Requires-Dist: scipy (<1.14)
Requires-Dist: shap (>=0.44.1,<0.45.0)
Requires-Dist: statsmodels (>=0.14.2,<0.15.0)
Requires-Dist: tabulate (>=0.9.0,<0.10.0)
Requires-Dist: tqdm (>=4.66.0,<5.0.0)
Requires-Dist: xgboost (>=2.1.1,<3.0.0)
